shurl/__init__.py
shurl/shurl.py
shurl-1.0.1.dist-info/METADATA
shurl-1.0.1.dist-info/WHEEL
shurl-1.0.1.dist-info/entry_points.txt
shurl-1.0.1.dist-info/top_level.txt
shurl-1.0.1.dist-info/RECORD
